arztalepkutuphanesi/__init__.py
arztalepkutuphanesi/arztalepcekme.py
tests/__init__.py
tests/test_arztalepcekme.py
arztalepkutuphanesi-0.1.3.dist-info/METADATA
arztalepkutuphanesi-0.1.3.dist-info/WHEEL
arztalepkutuphanesi-0.1.3.dist-info/top_level.txt
arztalepkutuphanesi-0.1.3.dist-info/RECORD
